[
    {
        "@id": "https://openebench.bsc.es/monitor/metrics/bioconda:perl-json-xs:4.02/cmd/metacpan.org",
        "@license": "https://creativecommons.org/licenses/by/4.0/",
        "@nmsp": "bioconda",
        "@timestamp": "2023-09-30T03:02:41.203277Z",
        "@type": "metrics",
        "distribution": {
            "packages": true,
            "sourcecode": {}
        },
        "project": {
            "build": {},
            "deployment": {},
            "license": {
                "open_source": false,
                "osi": false
            },
            "publications": [],
            "summary": {
                "description": true
            },
            "website": {
                "access_time": 32,
                "bioschemas": false,
                "copyright": false,
                "half_year_stat": [
                    {
                        "days": 183,
                        "serie": [
                            183
                        ],
                        "status": 200
                    }
                ],
                "https": true,
                "last_check": "2023-09-30T03:02:41.135283Z",
                "last_month_access": {
                    "average_access_time": 314,
                    "downtime_days": 0,
                    "uptime_days": 30
                },
                "license": false,
                "operational": 200,
                "redirects": [
                    {
                        "status": 301,
                        "url": "https://metacpan.org/pod/JSON::XS"
                    }
                ],
                "ssl": true,
                "ssl_err": null
            }
        }
    },
    {
        "@id": "https://openebench.bsc.es/monitor/metrics/bioconda:perl-json-xs:4.0/cmd/metacpan.org",
        "@license": "https://creativecommons.org/licenses/by/4.0/",
        "@nmsp": "bioconda",
        "@timestamp": "2023-09-30T03:01:28.814234Z",
        "@type": "metrics",
        "distribution": {
            "packages": true,
            "sourcecode": {}
        },
        "project": {
            "build": {},
            "deployment": {},
            "license": {
                "open_source": false,
                "osi": false
            },
            "publications": [],
            "summary": {
                "description": true
            },
            "website": {
                "access_time": 33,
                "bioschemas": false,
                "copyright": false,
                "half_year_stat": [
                    {
                        "days": 1,
                        "serie": [
                            1
                        ],
                        "status": 503
                    },
                    {
                        "days": 182,
                        "serie": [
                            17,
                            165
                        ],
                        "status": 200
                    }
                ],
                "https": true,
                "last_check": "2023-09-30T03:01:28.760345Z",
                "last_month_access": {
                    "average_access_time": 204,
                    "downtime_days": 0,
                    "uptime_days": 30
                },
                "license": false,
                "operational": 200,
                "redirects": [
                    {
                        "status": 301,
                        "url": "https://metacpan.org/pod/JSON::XS"
                    }
                ],
                "ssl": true,
                "ssl_err": null
            }
        }
    },
    {
        "@id": "https://openebench.bsc.es/monitor/metrics/bioconda:perl-json-xs:3.04/cmd/metacpan.org",
        "@license": "https://creativecommons.org/licenses/by/4.0/",
        "@nmsp": "bioconda",
        "@timestamp": "2023-09-30T02:59:13.879186Z",
        "@type": "metrics",
        "distribution": {
            "packages": true,
            "sourcecode": {}
        },
        "project": {
            "build": {},
            "deployment": {},
            "license": {
                "open_source": false,
                "osi": false
            },
            "publications": [],
            "summary": {
                "description": true
            },
            "website": {
                "access_time": 38,
                "bioschemas": false,
                "copyright": false,
                "half_year_stat": [
                    {
                        "days": 1,
                        "serie": [
                            1
                        ],
                        "status": 503
                    },
                    {
                        "days": 182,
                        "serie": [
                            17,
                            165
                        ],
                        "status": 200
                    }
                ],
                "https": true,
                "last_check": "2023-09-30T02:59:13.808145Z",
                "last_month_access": {
                    "average_access_time": 136,
                    "downtime_days": 0,
                    "uptime_days": 30
                },
                "license": false,
                "operational": 200,
                "redirects": [
                    {
                        "status": 301,
                        "url": "https://metacpan.org/pod/JSON::XS"
                    }
                ],
                "ssl": true,
                "ssl_err": null
            }
        }
    },
    {
        "@id": "https://openebench.bsc.es/monitor/metrics/bioconda:perl-json-xs:2.34/cmd/metacpan.org",
        "@license": "https://creativecommons.org/licenses/by/4.0/",
        "@nmsp": "bioconda",
        "@timestamp": "2023-09-30T02:58:40.603069Z",
        "@type": "metrics",
        "distribution": {
            "packages": true,
            "sourcecode": {}
        },
        "project": {
            "build": {},
            "deployment": {},
            "license": {
                "open_source": false,
                "osi": false
            },
            "publications": [],
            "summary": {
                "description": true
            },
            "website": {
                "access_time": 1595,
                "bioschemas": false,
                "copyright": false,
                "half_year_stat": [
                    {
                        "days": 2,
                        "serie": [
                            1,
                            1
                        ],
                        "status": 503
                    },
                    {
                        "days": 181,
                        "serie": [
                            17,
                            94,
                            70
                        ],
                        "status": 200
                    }
                ],
                "https": true,
                "last_check": "2023-09-30T02:58:40.54692Z",
                "last_month_access": {
                    "average_access_time": 1439,
                    "downtime_days": 0,
                    "uptime_days": 30
                },
                "license": false,
                "operational": 200,
                "redirects": [
                    {
                        "status": 301,
                        "url": "https://metacpan.org/pod/JSON::XS"
                    }
                ],
                "ssl": true,
                "ssl_err": null
            }
        }
    },
    {
        "@id": "https://openebench.bsc.es/monitor/metrics/bioconda:perl-json-xs:2.34/cmd/search.cpan.org",
        "@license": "https://creativecommons.org/licenses/by/4.0/",
        "@nmsp": "bioconda",
        "@timestamp": "2023-09-30T03:02:53.219278Z",
        "@type": "metrics",
        "distribution": {
            "packages": true,
            "sourcecode": {}
        },
        "project": {
            "build": {},
            "deployment": {},
            "license": {
                "open_source": false,
                "osi": false
            },
            "publications": [],
            "summary": {
                "description": true
            },
            "website": {
                "access_time": 1377,
                "bioschemas": false,
                "copyright": false,
                "half_year_stat": [
                    {
                        "days": 183,
                        "serie": [
                            183
                        ],
                        "status": 200
                    }
                ],
                "https": true,
                "last_check": "2023-09-30T03:02:53.167964Z",
                "last_month_access": {
                    "average_access_time": 1255,
                    "downtime_days": 0,
                    "uptime_days": 30
                },
                "license": false,
                "operational": 200,
                "redirects": [
                    {
                        "status": 301,
                        "url": "https://metacpan.org/release/JSON-XS"
                    },
                    {
                        "status": 301,
                        "url": "https://metacpan.org/dist/JSON-XS"
                    }
                ],
                "ssl": true,
                "ssl_err": null
            }
        }
    },
    {
        "@id": "https://openebench.bsc.es/monitor/metrics/perl-json-xs",
        "@license": "https://creativecommons.org/licenses/by/4.0/",
        "@nmsp": null,
        "@timestamp": "2023-09-30T03:02:53.471172Z",
        "@type": "metrics",
        "project": {
            "build": {},
            "deployment": {},
            "publications": [],
            "summary": {
                "description": true
            },
            "website": {
                "access_time": 33,
                "bioschemas": false,
                "copyright": false,
                "half_year_stat": [
                    {
                        "days": 183,
                        "serie": [
                            183
                        ],
                        "status": 200
                    }
                ],
                "https": true,
                "last_check": "2023-09-30T03:02:53.365133Z",
                "last_month_access": {
                    "average_access_time": 39,
                    "downtime_days": 0,
                    "uptime_days": 30
                },
                "license": false,
                "operational": 200,
                "redirects": [
                    {
                        "status": 301,
                        "url": "https://metacpan.org/pod/JSON::XS"
                    }
                ],
                "ssl": true,
                "ssl_err": null
            }
        }
    },
    {
        "@id": "https://openebench.bsc.es/monitor/metrics/bioconda:perl-json-xs:4.03/cmd/metacpan.org",
        "@license": "https://creativecommons.org/licenses/by/4.0/",
        "@nmsp": "bioconda",
        "@timestamp": "2023-09-30T06:20:36.455101Z",
        "@type": "metrics",
        "distribution": {
            "packages": true,
            "sourcecode": {}
        },
        "project": {
            "build": {},
            "deployment": {},
            "license": {
                "open_source": false,
                "osi": false
            },
            "publications": [],
            "summary": {
                "description": true
            },
            "website": {
                "access_time": 1440,
                "bioschemas": false,
                "copyright": false,
                "half_year_stat": [
                    {
                        "days": 1,
                        "serie": [
                            1
                        ],
                        "status": 503
                    },
                    {
                        "days": 182,
                        "serie": [
                            158,
                            24
                        ],
                        "status": 200
                    }
                ],
                "https": true,
                "last_check": "2023-09-30T06:20:36.387539Z",
                "last_month_access": {
                    "average_access_time": 1655,
                    "downtime_days": 1,
                    "uptime_days": 29
                },
                "license": false,
                "operational": 200,
                "redirects": [
                    {
                        "status": 301,
                        "url": "https://metacpan.org/pod/JSON::XS"
                    }
                ],
                "ssl": true,
                "ssl_err": null
            }
        }
    }
]