[
    {
        "@id": "https://openebench.bsc.es/monitor/metrics/bioconductor-hmp16sdata",
        "@license": "https://creativecommons.org/licenses/by/4.0/",
        "@nmsp": null,
        "@timestamp": "2022-10-01T09:18:34.013932Z",
        "@type": "metrics",
        "project": {
            "build": {},
            "deployment": {},
            "publications": [],
            "summary": {
                "description": true
            },
            "website": {
                "access_time": 124,
                "bioschemas": false,
                "copyright": false,
                "half_year_stat": [
                    {
                        "days": 182,
                        "serie": [
                            182
                        ],
                        "status": 200
                    }
                ],
                "https": true,
                "last_check": "2022-10-01T09:18:33.972276Z",
                "last_month_access": {
                    "average_access_time": 134,
                    "downtime_days": 0,
                    "uptime_days": 21
                },
                "license": false,
                "operational": 200,
                "ssl": true,
                "ssl_err": null
            }
        }
    },
    {
        "@id": "https://openebench.bsc.es/monitor/metrics/bioconda:bioconductor-hmp16sdata:1.4.1/cmd/bioconductor.org",
        "@license": "https://creativecommons.org/licenses/by/4.0/",
        "@nmsp": "bioconda",
        "@timestamp": "2022-10-01T09:18:37.207301Z",
        "@type": "metrics",
        "distribution": {
            "packages": true,
            "sourcecode": {}
        },
        "project": {
            "build": {},
            "deployment": {},
            "license": {
                "open_source": true,
                "osi": true
            },
            "publications": [],
            "summary": {
                "description": true
            },
            "website": {
                "access_time": 125,
                "bioschemas": false,
                "copyright": false,
                "half_year_stat": [
                    {
                        "days": 182,
                        "serie": [
                            182
                        ],
                        "status": 200
                    }
                ],
                "https": true,
                "last_check": "2022-10-01T09:18:37.156429Z",
                "last_month_access": {
                    "average_access_time": 139,
                    "downtime_days": 0,
                    "uptime_days": 21
                },
                "license": false,
                "operational": 200,
                "ssl": true,
                "ssl_err": null
            }
        }
    },
    {
        "@id": "https://openebench.bsc.es/monitor/metrics/bioconda:bioconductor-hmp16sdata:1.10.0/cmd/bioconductor.org",
        "@license": "https://creativecommons.org/licenses/by/4.0/",
        "@nmsp": "bioconda",
        "@timestamp": "2022-10-01T09:20:27.808666Z",
        "@type": "metrics",
        "distribution": {
            "packages": true,
            "sourcecode": {}
        },
        "project": {
            "build": {},
            "deployment": {},
            "license": {
                "open_source": true,
                "osi": true
            },
            "publications": [],
            "summary": {
                "description": true
            },
            "website": {
                "access_time": 129,
                "bioschemas": false,
                "copyright": false,
                "half_year_stat": [
                    {
                        "days": 182,
                        "serie": [
                            182
                        ],
                        "status": 200
                    }
                ],
                "https": true,
                "last_check": "2022-10-01T09:20:27.733085Z",
                "last_month_access": {
                    "average_access_time": 132,
                    "downtime_days": 0,
                    "uptime_days": 21
                },
                "license": false,
                "operational": 200,
                "ssl": true,
                "ssl_err": null
            }
        }
    },
    {
        "@id": "https://openebench.bsc.es/monitor/metrics/bioconda:bioconductor-hmp16sdata:1.6.0/cmd/bioconductor.org",
        "@license": "https://creativecommons.org/licenses/by/4.0/",
        "@nmsp": "bioconda",
        "@timestamp": "2022-10-01T09:21:34.695299Z",
        "@type": "metrics",
        "distribution": {
            "packages": true,
            "sourcecode": {}
        },
        "project": {
            "build": {},
            "deployment": {},
            "license": {
                "open_source": true,
                "osi": true
            },
            "publications": [],
            "summary": {
                "description": true
            },
            "website": {
                "access_time": 209,
                "bioschemas": false,
                "copyright": false,
                "half_year_stat": [
                    {
                        "days": 182,
                        "serie": [
                            182
                        ],
                        "status": 200
                    }
                ],
                "https": true,
                "last_check": "2022-10-01T09:21:34.657907Z",
                "last_month_access": {
                    "average_access_time": 131,
                    "downtime_days": 0,
                    "uptime_days": 21
                },
                "license": false,
                "operational": 200,
                "ssl": true,
                "ssl_err": null
            }
        }
    },
    {
        "@id": "https://openebench.bsc.es/monitor/metrics/bioconda:bioconductor-hmp16sdata:1.8.0/cmd/bioconductor.org",
        "@license": "https://creativecommons.org/licenses/by/4.0/",
        "@nmsp": "bioconda",
        "@timestamp": "2022-10-01T09:21:42.565858Z",
        "@type": "metrics",
        "distribution": {
            "packages": true,
            "sourcecode": {}
        },
        "project": {
            "build": {},
            "deployment": {},
            "license": {
                "open_source": true,
                "osi": true
            },
            "publications": [],
            "summary": {
                "description": true
            },
            "website": {
                "access_time": 120,
                "bioschemas": false,
                "copyright": false,
                "half_year_stat": [
                    {
                        "days": 182,
                        "serie": [
                            182
                        ],
                        "status": 200
                    }
                ],
                "https": true,
                "last_check": "2022-10-01T09:21:42.529672Z",
                "last_month_access": {
                    "average_access_time": 147,
                    "downtime_days": 0,
                    "uptime_days": 21
                },
                "license": false,
                "operational": 200,
                "ssl": true,
                "ssl_err": null
            }
        }
    },
    {
        "@id": "https://openebench.bsc.es/monitor/metrics/bioconda:bioconductor-hmp16sdata:1.2.0/cmd/bioconductor.org",
        "@license": "https://creativecommons.org/licenses/by/4.0/",
        "@nmsp": "bioconda",
        "@timestamp": "2022-10-01T09:22:51.957824Z",
        "@type": "metrics",
        "distribution": {
            "packages": true,
            "sourcecode": {}
        },
        "project": {
            "build": {},
            "deployment": {},
            "license": {
                "open_source": true,
                "osi": true
            },
            "publications": [],
            "summary": {
                "description": true
            },
            "website": {
                "access_time": 133,
                "bioschemas": false,
                "copyright": false,
                "half_year_stat": [
                    {
                        "days": 182,
                        "serie": [
                            182
                        ],
                        "status": 200
                    }
                ],
                "https": true,
                "last_check": "2022-10-01T09:22:51.91985Z",
                "last_month_access": {
                    "average_access_time": 153,
                    "downtime_days": 0,
                    "uptime_days": 21
                },
                "license": false,
                "operational": 200,
                "ssl": true,
                "ssl_err": null
            }
        }
    },
    {
        "@id": "https://openebench.bsc.es/monitor/metrics/bioconda:bioconductor-hmp16sdata:1.12.0/cmd/bioconductor.org",
        "@license": "https://creativecommons.org/licenses/by/4.0/",
        "@nmsp": "bioconda",
        "@timestamp": "2022-10-01T09:24:27.308775Z",
        "@type": "metrics",
        "distribution": {
            "packages": true,
            "sourcecode": {}
        },
        "project": {
            "build": {},
            "deployment": {},
            "license": {
                "open_source": true,
                "osi": true
            },
            "publications": [],
            "summary": {
                "description": true
            },
            "website": {
                "access_time": 129,
                "bioschemas": false,
                "copyright": false,
                "half_year_stat": [
                    {
                        "days": 182,
                        "serie": [
                            182
                        ],
                        "status": 200
                    }
                ],
                "https": true,
                "last_check": "2022-10-01T09:24:27.260269Z",
                "last_month_access": {
                    "average_access_time": 147,
                    "downtime_days": 0,
                    "uptime_days": 21
                },
                "license": false,
                "operational": 200,
                "ssl": true,
                "ssl_err": null
            }
        }
    },
    {
        "@id": "https://openebench.bsc.es/monitor/metrics/bioconda:bioconductor-hmp16sdata:1.14.0/cmd/bioconductor.org",
        "@license": "https://creativecommons.org/licenses/by/4.0/",
        "@nmsp": "bioconda",
        "@timestamp": "2022-10-01T09:37:36.689835Z",
        "@type": "metrics",
        "distribution": {
            "packages": true,
            "sourcecode": {}
        },
        "project": {
            "build": {},
            "deployment": {},
            "license": {
                "open_source": true,
                "osi": true
            },
            "publications": [],
            "summary": {
                "description": true
            },
            "website": {
                "access_time": 124,
                "bioschemas": false,
                "copyright": false,
                "half_year_stat": [
                    {
                        "days": 182,
                        "serie": [
                            182
                        ],
                        "status": 200
                    }
                ],
                "https": true,
                "last_check": "2022-10-01T09:18:33.972276Z",
                "last_month_access": {
                    "average_access_time": 131,
                    "downtime_days": 0,
                    "uptime_days": 21
                },
                "license": false,
                "operational": 200,
                "ssl": true,
                "ssl_err": null
            }
        }
    }
]