[
    {
        "@id": "https://openebench.bsc.es/monitor/metrics/bioconda:rgraphviz:2.13.0/cmd/bioconductor.org",
        "@license": "https://creativecommons.org/licenses/by/4.0/",
        "@nmsp": "bioconda",
        "@timestamp": "2023-01-07T07:36:33.027857Z",
        "@type": "metrics",
        "distribution": {
            "packages": true,
            "sourcecode": {}
        },
        "project": {
            "build": {},
            "deployment": {},
            "license": {
                "open_source": false,
                "osi": false
            },
            "publications": [
                {
                    "entries": [
                        {
                            "cit_count": 1451,
                            "citations": [
                                {
                                    "count": 27,
                                    "year": "2015"
                                },
                                {
                                    "count": 151,
                                    "year": "2016"
                                },
                                {
                                    "count": 188,
                                    "year": "2017"
                                },
                                {
                                    "count": 235,
                                    "year": "2018"
                                },
                                {
                                    "count": 245,
                                    "year": "2019"
                                },
                                {
                                    "count": 219,
                                    "year": "2020"
                                },
                                {
                                    "count": 266,
                                    "year": "2021"
                                },
                                {
                                    "count": 120,
                                    "year": "2022"
                                }
                            ],
                            "doi": "10.1038/nmeth.3252",
                            "pmcid": "PMC4509590",
                            "pmid": "25633503",
                            "ref_count": 27,
                            "refs": [
                                {
                                    "count": 1,
                                    "year": "2001"
                                },
                                {
                                    "count": 1,
                                    "year": "2004"
                                },
                                {
                                    "count": 2,
                                    "year": "2005"
                                },
                                {
                                    "count": 2,
                                    "year": "2007"
                                },
                                {
                                    "count": 1,
                                    "year": "2008"
                                },
                                {
                                    "count": 1,
                                    "year": "2009"
                                },
                                {
                                    "count": 2,
                                    "year": "2010"
                                },
                                {
                                    "count": 2,
                                    "year": "2012"
                                },
                                {
                                    "count": 3,
                                    "year": "2013"
                                },
                                {
                                    "count": 12,
                                    "year": "2014"
                                }
                            ],
                            "title": "Orchestrating high-throughput genomic analysis with Bioconductor.",
                            "year": 2015
                        }
                    ]
                }
            ],
            "summary": {
                "description": true
            },
            "website": {
                "access_time": 127,
                "bioschemas": false,
                "copyright": false,
                "half_year_stat": [
                    {
                        "days": 183,
                        "serie": [
                            183
                        ],
                        "status": 200
                    }
                ],
                "https": false,
                "last_check": "2023-01-07T02:31:03.699195Z",
                "last_month_access": {
                    "average_access_time": 142,
                    "downtime_days": 0,
                    "uptime_days": 30
                },
                "license": false,
                "operational": 200,
                "ssl": null,
                "ssl_err": null
            }
        }
    },
    {
        "@id": "https://openebench.bsc.es/monitor/metrics/bioconda:rgraphviz:2.20.0/cmd/bioconductor.org",
        "@license": "https://creativecommons.org/licenses/by/4.0/",
        "@nmsp": "bioconda",
        "@timestamp": "2023-01-07T07:38:38.979914Z",
        "@type": "metrics",
        "distribution": {
            "packages": true,
            "sourcecode": {}
        },
        "project": {
            "build": {},
            "deployment": {},
            "license": {
                "open_source": false,
                "osi": false
            },
            "publications": [],
            "summary": {
                "description": true
            },
            "website": {
                "access_time": 123,
                "bioschemas": false,
                "copyright": false,
                "half_year_stat": [
                    {
                        "days": 183,
                        "serie": [
                            183
                        ],
                        "status": 200
                    }
                ],
                "https": false,
                "last_check": "2023-01-07T02:31:43.400133Z",
                "last_month_access": {
                    "average_access_time": 146,
                    "downtime_days": 0,
                    "uptime_days": 30
                },
                "license": false,
                "operational": 200,
                "ssl": null,
                "ssl_err": null
            }
        }
    },
    {
        "@id": "https://openebench.bsc.es/monitor/metrics/bioconda:rgraphviz:2.28.0/cmd/bioconductor.org",
        "@license": "https://creativecommons.org/licenses/by/4.0/",
        "@nmsp": "bioconda",
        "@timestamp": "2023-01-07T07:50:11.830174Z",
        "@type": "metrics",
        "distribution": {
            "packages": true,
            "sourcecode": {}
        },
        "project": {
            "build": {},
            "deployment": {},
            "license": {
                "open_source": false,
                "osi": false
            },
            "publications": [],
            "summary": {
                "description": true
            },
            "website": {
                "access_time": 123,
                "bioschemas": false,
                "copyright": false,
                "half_year_stat": [
                    {
                        "days": 183,
                        "serie": [
                            183
                        ],
                        "status": 200
                    }
                ],
                "https": true,
                "last_check": "2023-01-07T02:34:06.160999Z",
                "last_month_access": {
                    "average_access_time": 142,
                    "downtime_days": 0,
                    "uptime_days": 30
                },
                "license": false,
                "operational": 200,
                "ssl": true,
                "ssl_err": null
            }
        }
    },
    {
        "@id": "https://openebench.bsc.es/monitor/metrics/bioconda:rgraphviz:2.26.0/cmd/bioconductor.org",
        "@license": "https://creativecommons.org/licenses/by/4.0/",
        "@nmsp": "bioconda",
        "@timestamp": "2023-01-07T07:36:15.837486Z",
        "@type": "metrics",
        "distribution": {
            "packages": true,
            "sourcecode": {}
        },
        "project": {
            "build": {},
            "deployment": {},
            "license": {
                "open_source": false,
                "osi": false
            },
            "publications": [],
            "summary": {
                "description": true
            },
            "website": {
                "access_time": 204,
                "bioschemas": false,
                "copyright": false,
                "half_year_stat": [
                    {
                        "days": 183,
                        "serie": [
                            183
                        ],
                        "status": 200
                    }
                ],
                "https": true,
                "last_check": "2023-01-07T02:31:34.18628Z",
                "last_month_access": {
                    "average_access_time": 143,
                    "downtime_days": 0,
                    "uptime_days": 30
                },
                "license": false,
                "operational": 200,
                "ssl": true,
                "ssl_err": null
            }
        }
    },
    {
        "@id": "https://openebench.bsc.es/monitor/metrics/bioconda:rgraphviz:2.14.0/cmd/bioconductor.org",
        "@license": "https://creativecommons.org/licenses/by/4.0/",
        "@nmsp": "bioconda",
        "@timestamp": "2023-01-07T07:38:20.415123Z",
        "@type": "metrics",
        "distribution": {
            "packages": true,
            "sourcecode": {}
        },
        "project": {
            "build": {},
            "deployment": {},
            "license": {
                "open_source": false,
                "osi": false
            },
            "publications": [],
            "summary": {
                "description": true
            },
            "website": {
                "access_time": 127,
                "bioschemas": false,
                "copyright": false,
                "half_year_stat": [
                    {
                        "days": 183,
                        "serie": [
                            183
                        ],
                        "status": 200
                    }
                ],
                "https": false,
                "last_check": "2023-01-07T02:31:03.699195Z",
                "last_month_access": {
                    "average_access_time": 142,
                    "downtime_days": 0,
                    "uptime_days": 30
                },
                "license": false,
                "operational": 200,
                "ssl": null,
                "ssl_err": null
            }
        }
    },
    {
        "@id": "https://openebench.bsc.es/monitor/metrics/bioconda:rgraphviz:2.22.0/cmd/bioconductor.org",
        "@license": "https://creativecommons.org/licenses/by/4.0/",
        "@nmsp": "bioconda",
        "@timestamp": "2023-01-07T07:33:54.268568Z",
        "@type": "metrics",
        "distribution": {
            "packages": true,
            "sourcecode": {}
        },
        "project": {
            "build": {},
            "deployment": {},
            "license": {
                "open_source": false,
                "osi": false
            },
            "publications": [],
            "summary": {
                "description": true
            },
            "website": {
                "access_time": 245,
                "bioschemas": false,
                "copyright": false,
                "half_year_stat": [
                    {
                        "days": 183,
                        "serie": [
                            183
                        ],
                        "status": 200
                    }
                ],
                "https": false,
                "last_check": "2023-01-07T02:42:03.461975Z",
                "last_month_access": {
                    "average_access_time": 221,
                    "downtime_days": 0,
                    "uptime_days": 30
                },
                "license": false,
                "operational": 200,
                "ssl": null,
                "ssl_err": null
            }
        }
    },
    {
        "@id": "https://openebench.bsc.es/monitor/metrics/bioconda:rgraphviz:2.16.0/cmd/bioconductor.org",
        "@license": "https://creativecommons.org/licenses/by/4.0/",
        "@nmsp": "bioconda",
        "@timestamp": "2023-01-07T07:49:18.942533Z",
        "@type": "metrics",
        "distribution": {
            "packages": true,
            "sourcecode": {}
        },
        "project": {
            "build": {},
            "deployment": {},
            "license": {
                "open_source": false,
                "osi": false
            },
            "publications": [],
            "summary": {
                "description": true
            },
            "website": {
                "access_time": 127,
                "bioschemas": false,
                "copyright": false,
                "half_year_stat": [
                    {
                        "days": 183,
                        "serie": [
                            183
                        ],
                        "status": 200
                    }
                ],
                "https": false,
                "last_check": "2023-01-07T02:31:03.699195Z",
                "last_month_access": {
                    "average_access_time": 142,
                    "downtime_days": 0,
                    "uptime_days": 30
                },
                "license": false,
                "operational": 200,
                "ssl": null,
                "ssl_err": null
            }
        }
    },
    {
        "@id": "https://openebench.bsc.es/monitor/metrics/bioconda:rgraphviz:2.24.0/cmd/bioconductor.org",
        "@license": "https://creativecommons.org/licenses/by/4.0/",
        "@nmsp": "bioconda",
        "@timestamp": "2023-01-07T07:43:21.063222Z",
        "@type": "metrics",
        "distribution": {
            "packages": true,
            "sourcecode": {}
        },
        "project": {
            "build": {},
            "deployment": {},
            "license": {
                "open_source": false,
                "osi": false
            },
            "publications": [
                {
                    "entries": [
                        {
                            "cit_count": 1451,
                            "citations": [
                                {
                                    "count": 27,
                                    "year": "2015"
                                },
                                {
                                    "count": 151,
                                    "year": "2016"
                                },
                                {
                                    "count": 188,
                                    "year": "2017"
                                },
                                {
                                    "count": 235,
                                    "year": "2018"
                                },
                                {
                                    "count": 245,
                                    "year": "2019"
                                },
                                {
                                    "count": 219,
                                    "year": "2020"
                                },
                                {
                                    "count": 266,
                                    "year": "2021"
                                },
                                {
                                    "count": 120,
                                    "year": "2022"
                                }
                            ],
                            "doi": "10.1038/nmeth.3252",
                            "pmcid": "PMC4509590",
                            "pmid": "25633503",
                            "ref_count": 27,
                            "refs": [
                                {
                                    "count": 1,
                                    "year": "2001"
                                },
                                {
                                    "count": 1,
                                    "year": "2004"
                                },
                                {
                                    "count": 2,
                                    "year": "2005"
                                },
                                {
                                    "count": 2,
                                    "year": "2007"
                                },
                                {
                                    "count": 1,
                                    "year": "2008"
                                },
                                {
                                    "count": 1,
                                    "year": "2009"
                                },
                                {
                                    "count": 2,
                                    "year": "2010"
                                },
                                {
                                    "count": 2,
                                    "year": "2012"
                                },
                                {
                                    "count": 3,
                                    "year": "2013"
                                },
                                {
                                    "count": 12,
                                    "year": "2014"
                                }
                            ],
                            "title": "Orchestrating high-throughput genomic analysis with Bioconductor.",
                            "year": 2015
                        }
                    ]
                }
            ],
            "summary": {
                "description": true
            },
            "website": {
                "access_time": 124,
                "bioschemas": false,
                "copyright": false,
                "half_year_stat": [
                    {
                        "days": 183,
                        "serie": [
                            183
                        ],
                        "status": 200
                    }
                ],
                "https": false,
                "last_check": "2023-01-07T07:43:20.96831Z",
                "last_month_access": {
                    "average_access_time": 123,
                    "downtime_days": 0,
                    "uptime_days": 30
                },
                "license": false,
                "operational": 200,
                "ssl": null,
                "ssl_err": null
            }
        }
    },
    {
        "@id": "https://openebench.bsc.es/monitor/metrics/biotools:rgraphviz:2.18.0/cmd/bioconductor.org",
        "@license": "https://creativecommons.org/licenses/by/4.0/",
        "@nmsp": "biotools",
        "@timestamp": "2023-01-07T07:52:09.722555Z",
        "@type": "metrics",
        "distribution": {
            "sourcecode": {
                "interpreted": true
            }
        },
        "project": {
            "build": {},
            "deployment": {},
            "documentation": {
                "manual": true
            },
            "license": {
                "open_source": true,
                "osi": true
            },
            "publications": [
                {
                    "entries": [
                        {
                            "cit_count": 1451,
                            "citations": [
                                {
                                    "count": 27,
                                    "year": "2015"
                                },
                                {
                                    "count": 151,
                                    "year": "2016"
                                },
                                {
                                    "count": 188,
                                    "year": "2017"
                                },
                                {
                                    "count": 235,
                                    "year": "2018"
                                },
                                {
                                    "count": 245,
                                    "year": "2019"
                                },
                                {
                                    "count": 219,
                                    "year": "2020"
                                },
                                {
                                    "count": 266,
                                    "year": "2021"
                                },
                                {
                                    "count": 120,
                                    "year": "2022"
                                }
                            ],
                            "doi": "10.1038/nmeth.3252",
                            "pmcid": "PMC4509590",
                            "pmid": "25633503",
                            "ref_count": 27,
                            "refs": [
                                {
                                    "count": 1,
                                    "year": "2001"
                                },
                                {
                                    "count": 1,
                                    "year": "2004"
                                },
                                {
                                    "count": 2,
                                    "year": "2005"
                                },
                                {
                                    "count": 2,
                                    "year": "2007"
                                },
                                {
                                    "count": 1,
                                    "year": "2008"
                                },
                                {
                                    "count": 1,
                                    "year": "2009"
                                },
                                {
                                    "count": 2,
                                    "year": "2010"
                                },
                                {
                                    "count": 2,
                                    "year": "2012"
                                },
                                {
                                    "count": 3,
                                    "year": "2013"
                                },
                                {
                                    "count": 12,
                                    "year": "2014"
                                }
                            ],
                            "title": "Orchestrating high-throughput genomic analysis with Bioconductor.",
                            "year": 2015
                        }
                    ]
                }
            ],
            "summary": {
                "description": true
            },
            "website": {
                "access_time": 127,
                "bioschemas": false,
                "copyright": false,
                "half_year_stat": [
                    {
                        "days": 183,
                        "serie": [
                            183
                        ],
                        "status": 200
                    }
                ],
                "https": false,
                "last_check": "2023-01-07T02:31:03.699195Z",
                "last_month_access": {
                    "average_access_time": 142,
                    "downtime_days": 0,
                    "uptime_days": 30
                },
                "license": false,
                "operational": 200,
                "ssl": null,
                "ssl_err": null
            }
        },
        "support": {
            "email": true
        }
    },
    {
        "@id": "https://openebench.bsc.es/monitor/metrics/biotools:rgraphviz:2.18.0/lib/bioconductor.org",
        "@license": "https://creativecommons.org/licenses/by/4.0/",
        "@nmsp": "biotools",
        "@timestamp": "2023-01-07T07:31:30.945476Z",
        "@type": "metrics",
        "distribution": {
            "sourcecode": {
                "interpreted": true
            }
        },
        "project": {
            "build": {},
            "deployment": {},
            "documentation": {
                "manual": true
            },
            "license": {
                "open_source": true,
                "osi": true
            },
            "publications": [
                {
                    "entries": [
                        {
                            "cit_count": 1451,
                            "citations": [
                                {
                                    "count": 27,
                                    "year": "2015"
                                },
                                {
                                    "count": 151,
                                    "year": "2016"
                                },
                                {
                                    "count": 188,
                                    "year": "2017"
                                },
                                {
                                    "count": 235,
                                    "year": "2018"
                                },
                                {
                                    "count": 245,
                                    "year": "2019"
                                },
                                {
                                    "count": 219,
                                    "year": "2020"
                                },
                                {
                                    "count": 266,
                                    "year": "2021"
                                },
                                {
                                    "count": 120,
                                    "year": "2022"
                                }
                            ],
                            "doi": "10.1038/nmeth.3252",
                            "pmcid": "PMC4509590",
                            "pmid": "25633503",
                            "ref_count": 27,
                            "refs": [
                                {
                                    "count": 1,
                                    "year": "2001"
                                },
                                {
                                    "count": 1,
                                    "year": "2004"
                                },
                                {
                                    "count": 2,
                                    "year": "2005"
                                },
                                {
                                    "count": 2,
                                    "year": "2007"
                                },
                                {
                                    "count": 1,
                                    "year": "2008"
                                },
                                {
                                    "count": 1,
                                    "year": "2009"
                                },
                                {
                                    "count": 2,
                                    "year": "2010"
                                },
                                {
                                    "count": 2,
                                    "year": "2012"
                                },
                                {
                                    "count": 3,
                                    "year": "2013"
                                },
                                {
                                    "count": 12,
                                    "year": "2014"
                                }
                            ],
                            "title": "Orchestrating high-throughput genomic analysis with Bioconductor.",
                            "year": 2015
                        }
                    ]
                }
            ],
            "summary": {
                "description": true
            },
            "website": {
                "access_time": 127,
                "bioschemas": false,
                "copyright": false,
                "half_year_stat": [
                    {
                        "days": 183,
                        "serie": [
                            183
                        ],
                        "status": 200
                    }
                ],
                "https": false,
                "last_check": "2023-01-07T02:31:03.699195Z",
                "last_month_access": {
                    "average_access_time": 142,
                    "downtime_days": 0,
                    "uptime_days": 30
                },
                "license": false,
                "operational": 200,
                "ssl": null,
                "ssl_err": null
            }
        },
        "support": {
            "email": true
        }
    },
    {
        "@id": "https://openebench.bsc.es/monitor/metrics/rgraphviz",
        "@license": "https://creativecommons.org/licenses/by/4.0/",
        "@nmsp": null,
        "@timestamp": "2023-01-07T07:36:25.364373Z",
        "@type": "metrics",
        "project": {
            "build": {},
            "deployment": {},
            "publications": [],
            "summary": {
                "description": true
            },
            "website": {
                "access_time": 127,
                "bioschemas": false,
                "copyright": false,
                "half_year_stat": [
                    {
                        "days": 183,
                        "serie": [
                            183
                        ],
                        "status": 200
                    }
                ],
                "https": false,
                "last_check": "2023-01-07T02:31:03.699195Z",
                "last_month_access": {
                    "average_access_time": 142,
                    "downtime_days": 0,
                    "uptime_days": 30
                },
                "license": false,
                "operational": 200,
                "ssl": null,
                "ssl_err": null
            }
        }
    },
    {
        "@id": "https://openebench.bsc.es/monitor/metrics/bioconda:rgraphviz:2.30.0/cmd/bioconductor.org",
        "@license": "https://creativecommons.org/licenses/by/4.0/",
        "@nmsp": "bioconda",
        "@timestamp": "2023-01-07T09:22:54.116406Z",
        "@type": "metrics",
        "distribution": {
            "packages": true,
            "sourcecode": {}
        },
        "project": {
            "build": {},
            "deployment": {},
            "license": {
                "open_source": false,
                "osi": false
            },
            "publications": [],
            "summary": {
                "description": true
            },
            "website": {
                "access_time": 122,
                "bioschemas": false,
                "copyright": false,
                "half_year_stat": [
                    {
                        "days": 183,
                        "serie": [
                            183
                        ],
                        "status": 200
                    }
                ],
                "https": true,
                "last_check": "2023-01-07T09:22:54.067702Z",
                "last_month_access": {
                    "average_access_time": 132,
                    "downtime_days": 0,
                    "uptime_days": 30
                },
                "license": false,
                "operational": 200,
                "ssl": true,
                "ssl_err": null
            }
        }
    },
    {
        "@id": "https://openebench.bsc.es/monitor/metrics/bioconda:rgraphviz:2.32.0/cmd/bioconductor.org",
        "@license": "https://creativecommons.org/licenses/by/4.0/",
        "@nmsp": "bioconda",
        "@timestamp": "2023-01-07T09:24:40.253805Z",
        "@type": "metrics",
        "distribution": {
            "packages": true,
            "sourcecode": {}
        },
        "project": {
            "build": {},
            "deployment": {},
            "license": {
                "open_source": false,
                "osi": false
            },
            "publications": [],
            "summary": {
                "description": true
            },
            "website": {
                "access_time": 123,
                "bioschemas": false,
                "copyright": false,
                "half_year_stat": [
                    {
                        "days": 183,
                        "serie": [
                            183
                        ],
                        "status": 200
                    }
                ],
                "https": true,
                "last_check": "2023-01-07T09:24:40.191756Z",
                "last_month_access": {
                    "average_access_time": 131,
                    "downtime_days": 0,
                    "uptime_days": 30
                },
                "license": false,
                "operational": 200,
                "ssl": true,
                "ssl_err": null
            }
        }
    },
    {
        "@id": "https://openebench.bsc.es/monitor/metrics/bioconda:rgraphviz:2.34.0/cmd/bioconductor.org",
        "@license": "https://creativecommons.org/licenses/by/4.0/",
        "@nmsp": "bioconda",
        "@timestamp": "2023-01-07T09:26:09.286813Z",
        "@type": "metrics",
        "distribution": {
            "packages": true,
            "sourcecode": {}
        },
        "project": {
            "build": {},
            "deployment": {},
            "license": {
                "open_source": false,
                "osi": false
            },
            "publications": [],
            "summary": {
                "description": true
            },
            "website": {
                "access_time": 124,
                "bioschemas": false,
                "copyright": false,
                "half_year_stat": [
                    {
                        "days": 183,
                        "serie": [
                            183
                        ],
                        "status": 200
                    }
                ],
                "https": true,
                "last_check": "2023-01-07T09:26:09.218322Z",
                "last_month_access": {
                    "average_access_time": 148,
                    "downtime_days": 0,
                    "uptime_days": 30
                },
                "license": false,
                "operational": 200,
                "ssl": true,
                "ssl_err": null
            }
        }
    },
    {
        "@id": "https://openebench.bsc.es/monitor/metrics/bioconda:rgraphviz:2.36.0/cmd/bioconductor.org",
        "@license": "https://creativecommons.org/licenses/by/4.0/",
        "@nmsp": "bioconda",
        "@timestamp": "2023-01-07T09:57:13.949220Z",
        "@type": "metrics",
        "distribution": {
            "packages": true,
            "sourcecode": {}
        },
        "project": {
            "build": {},
            "deployment": {},
            "license": {
                "open_source": false,
                "osi": false
            },
            "publications": [],
            "summary": {
                "description": true
            },
            "website": {
                "access_time": 117,
                "bioschemas": false,
                "copyright": false,
                "half_year_stat": [
                    {
                        "days": 183,
                        "serie": [
                            183
                        ],
                        "status": 200
                    }
                ],
                "https": true,
                "last_check": "2023-01-07T09:57:13.902823Z",
                "last_month_access": {
                    "average_access_time": 132,
                    "downtime_days": 0,
                    "uptime_days": 30
                },
                "license": false,
                "operational": 200,
                "ssl": true,
                "ssl_err": null
            }
        }
    },
    {
        "@id": "https://openebench.bsc.es/monitor/metrics/bioconda:rgraphviz:2.38.0/cmd/bioconductor.org",
        "@license": "https://creativecommons.org/licenses/by/4.0/",
        "@nmsp": "bioconda",
        "@timestamp": "2023-01-07T10:11:36.260534Z",
        "@type": "metrics",
        "distribution": {
            "packages": true,
            "sourcecode": {}
        },
        "project": {
            "build": {},
            "deployment": {},
            "license": {
                "open_source": false,
                "osi": false
            },
            "publications": [],
            "summary": {
                "description": true
            },
            "website": {
                "access_time": 124,
                "bioschemas": false,
                "copyright": false,
                "half_year_stat": [
                    {
                        "days": 183,
                        "serie": [
                            183
                        ],
                        "status": 200
                    }
                ],
                "https": true,
                "last_check": "2023-01-07T10:11:36.228334Z",
                "last_month_access": {
                    "average_access_time": 133,
                    "downtime_days": 0,
                    "uptime_days": 30
                },
                "license": false,
                "operational": 200,
                "ssl": true,
                "ssl_err": null
            }
        }
    },
    {
        "@id": "https://openebench.bsc.es/monitor/metrics/bioconda:rgraphviz:2.42.0/cmd/bioconductor.org",
        "@license": "https://creativecommons.org/licenses/by/4.0/",
        "@nmsp": "bioconda",
        "@timestamp": "2023-01-07T10:45:59.034874Z",
        "@type": "metrics",
        "distribution": {
            "packages": true,
            "sourcecode": {}
        },
        "project": {
            "build": {},
            "deployment": {},
            "license": {
                "open_source": false,
                "osi": false
            },
            "publications": [],
            "summary": {
                "description": true
            },
            "website": {
                "access_time": 123,
                "bioschemas": false,
                "copyright": false,
                "half_year_stat": [
                    {
                        "days": 62,
                        "serie": [
                            62
                        ],
                        "status": 200
                    }
                ],
                "https": true,
                "last_check": "2023-01-07T10:45:59.013455Z",
                "last_month_access": {
                    "average_access_time": 130,
                    "downtime_days": 0,
                    "uptime_days": 30
                },
                "license": false,
                "operational": 200,
                "ssl": true,
                "ssl_err": null
            }
        }
    }
]